{
  "atlasParticipantId": "B4435",
  "atlasGroup": "Sage",
  "sex": "Female",
  "race": "White",
  "ethnicity": "not hispanic or latino",
  "ageAtMenarche": 13,
  "classBRCA1": "pathogenic",
  "classBRCA2": "variant of uncertain significance",
  "timepointLabel": "Main collection",
  "age": 45,
  "weight": 130,
  "menopauseStatus": "Premenopausal",
  "menopauseCycleStage": "unknown",
  "gravidity": 0,
  "parity": 0,
  "primaryDiagnosis": "none",
  "previousDiagnosis": "breast carcinoma",
  "tobaccoUse": "lifelong non-smoker",
  "packYearsSmoked": 0,
  "alcoholUse": "non-drinker",
  "drinksPerWeek": 0,
  "antibioticUse": "unknown",
  "sampleId": "R123",
  "sampleCollectionCenter": "MGH",
  "sampleSite": "right breast",
  "tumorGrade": "not applicable",
  "statusER": "unknown/not done",
  "statusPR": "unknown/not done",
  "statusHER2": "unknown/not done",
  "synData": [
    "syn36658206",
    "syn36658207"
  ]
}